[  
  {  
    "facility_id":1,
    "type":"User Short",
    "root_cause":"Replenishment",
    "wave_number":"Wave 1",
    "order_number":"Order 1",
    "order_status":"Shipped",
    "line_status":"Cancelled",
    "sku":"Item 1",
    "sku_description":"Item 1 Description",
    "std_sku_qty":1,
    "ordered_qty":12,
    "allocated_qty":12,
    "packed_qty":0,
    "shorted_qty":12,
    "shorted_by":"User 1",
    "shorted_datetime":"2016-09-22T23:47:48.000Z",
    "location":"Location 16",
    "active_on_hand_qty":0,
    "active_allocated_qty":12,
    "active_tbf_qty":72,
    "reserve_on_hand_qty":72,
    "reserve_allocated_qty":72,
    "reserve_tbf_qty":0,
    "transitional_qty":0,
    "unallocatable_qty":13,
    "drop_zone_on_hand_qty":0,
    "drop_zone_allocated_qty":0,
    "open_replen_tasks":0,
    "open_putaway_tasks":0,
    "open_asn_qty":5,
    "location_accuracy_score":0.8
  },
  {  
    "facility_id":1,
    "type":"User Short",
    "root_cause":"Replenishment",
    "wave_number":"Wave 1",
    "order_number":"Order 2",
    "order_status":"Packed",
    "line_status":"Cancelled",
    "sku":"Item 2",
    "sku_description":"Item 2 Description",
    "std_sku_qty":1,
    "ordered_qty":3,
    "allocated_qty":3,
    "packed_qty":0,
    "shorted_qty":3,
    "shorted_by":"User 2",
    "shorted_datetime":"2016-09-22T23:53:29.000Z",
    "location":"Location 17",
    "active_on_hand_qty":0,
    "active_allocated_qty":6,
    "active_tbf_qty":220,
    "reserve_on_hand_qty":1,
    "reserve_allocated_qty":10,
    "reserve_tbf_qty":0,
    "transitional_qty":0,
    "unallocatable_qty":1,
    "drop_zone_on_hand_qty":0,
    "drop_zone_allocated_qty":0,
    "open_replen_tasks":1,
    "open_putaway_tasks":0,
    "open_asn_qty":47,
    "location_accuracy_score":0.9
  },
  {  
    "facility_id":1,
    "type":"User Short",
    "root_cause":"Invn Accuracy",
    "wave_number":"Wave 1",
    "order_number":"Order 3",
    "order_status":"Loaded",
    "line_status":"Cancelled",
    "sku":"Item 3",
    "sku_description":"Item 3 Description",
    "std_sku_qty":1,
    "ordered_qty":2,
    "allocated_qty":2,
    "packed_qty":0,
    "shorted_qty":2,
    "shorted_by":"User 3",
    "shorted_datetime":"2016-09-22T23:51:37.000Z",
    "location":"Location 18",
    "active_on_hand_qty":447,
    "active_allocated_qty":4,
    "active_tbf_qty":0,
    "reserve_on_hand_qty":800,
    "reserve_allocated_qty":0,
    "reserve_tbf_qty":0,
    "transitional_qty":0,
    "unallocatable_qty":0,
    "drop_zone_on_hand_qty":0,
    "drop_zone_allocated_qty":0,
    "open_replen_tasks":2,
    "open_putaway_tasks":0,
    "open_asn_qty":5,
    "location_accuracy_score":0.95
  },
  {  
    "facility_id":1,
    "type":"User Short",
    "root_cause":"Invn Accuracy",
    "wave_number":"Wave 1",
    "order_number":"Order 4",
    "order_status":"In Packing",
    "line_status":"Packed",
    "sku":"Item 4",
    "sku_description":"Item 4 Description",
    "std_sku_qty":1,
    "ordered_qty":3,
    "allocated_qty":3,
    "packed_qty":1,
    "shorted_qty":2,
    "shorted_by":"User 4",
    "shorted_datetime":"2016-09-22T00:00:06.000Z",
    "location":"Location 19",
    "active_on_hand_qty":20,
    "active_allocated_qty":1,
    "active_tbf_qty":100,
    "reserve_on_hand_qty":120,
    "reserve_allocated_qty":100,
    "reserve_tbf_qty":20,
    "transitional_qty":0,
    "unallocatable_qty":0,
    "drop_zone_on_hand_qty":0,
    "drop_zone_allocated_qty":0,
    "open_replen_tasks":0,
    "open_putaway_tasks":0,
    "open_asn_qty":0,
    "location_accuracy_score":0.6
  },
  {  
    "facility_id":1,
    "type":"User Short",
    "root_cause":"Replenishment",
    "wave_number":"Wave 1",
    "order_number":"Order 5",
    "order_status":"In Packing",
    "line_status":"Cancelled",
    "sku":"Item 5",
    "sku_description":"Item 5 Description",
    "std_sku_qty":1,
    "ordered_qty":1,
    "allocated_qty":1,
    "packed_qty":0,
    "shorted_qty":1,
    "shorted_by":"User 5",
    "shorted_datetime":"2016-09-22T00:00:08.000Z",
    "location":"Location 20",
    "active_on_hand_qty":0,
    "active_allocated_qty":0,
    "active_tbf_qty":12,
    "reserve_on_hand_qty":105,
    "reserve_allocated_qty":0,
    "reserve_tbf_qty":0,
    "transitional_qty":0,
    "unallocatable_qty":0,
    "drop_zone_on_hand_qty":0,
    "drop_zone_allocated_qty":0,
    "open_replen_tasks":0,
    "open_putaway_tasks":0,
    "open_asn_qty":0,
    "location_accuracy_score":0.87
  },
  {  
    "facility_id":1,
    "type":"User Short",
    "root_cause":"Replenishment",
    "wave_number":"Wave 1",
    "order_number":"Order 6",
    "order_status":"In Packing",
    "line_status":"Cancelled",
    "sku":"Item 6",
    "sku_description":"Item 6 Description",
    "std_sku_qty":1,
    "ordered_qty":1,
    "allocated_qty":1,
    "packed_qty":0,
    "shorted_qty":1,
    "shorted_by":"User 6",
    "shorted_datetime":"2016-09-22T00:00:10.000Z",
    "location":"Location 21",
    "active_on_hand_qty":0,
    "active_allocated_qty":6,
    "active_tbf_qty":220,
    "reserve_on_hand_qty":1,
    "reserve_allocated_qty":10,
    "reserve_tbf_qty":0,
    "transitional_qty":0,
    "unallocatable_qty":1,
    "drop_zone_on_hand_qty":0,
    "drop_zone_allocated_qty":0,
    "open_replen_tasks":0,
    "open_putaway_tasks":0,
    "open_asn_qty":0,
    "location_accuracy_score":0.67
  },
  {  
    "facility_id":1,
    "type":"User Short",
    "root_cause":"Replenishment",
    "wave_number":"Wave 2",
    "order_number":"Order 7",
    "order_status":"In Packing",
    "line_status":"Cancelled",
    "sku":"Item 6",
    "sku_description":"Item 6 Description",
    "std_sku_qty":1,
    "ordered_qty":1,
    "allocated_qty":1,
    "packed_qty":0,
    "shorted_qty":1,
    "shorted_by":"User 7",
    "shorted_datetime":"2016-09-22T00:00:10.000Z",
    "location":"Location 22",
    "active_on_hand_qty":0,
    "active_allocated_qty":6,
    "active_tbf_qty":220,
    "reserve_on_hand_qty":1,
    "reserve_allocated_qty":10,
    "reserve_tbf_qty":0,
    "transitional_qty":0,
    "unallocatable_qty":1,
    "drop_zone_on_hand_qty":0,
    "drop_zone_allocated_qty":0,
    "open_replen_tasks":1,
    "open_putaway_tasks":0,
    "open_asn_qty":6,
    "location_accuracy_score":0.99
  },
  {  
    "facility_id":1,
    "type":"User Short",
    "root_cause":"Unknown",
    "wave_number":"Wave 3",
    "order_number":"Order 8",
    "order_status":"In Packing",
    "line_status":"Cancelled",
    "sku":"Item 7",
    "sku_description":"Item 7 Description",
    "std_sku_qty":1,
    "ordered_qty":1,
    "allocated_qty":1,
    "packed_qty":0,
    "shorted_qty":1,
    "shorted_by":"User 8",
    "shorted_datetime":"2016-09-20T00:00:18.000Z",
    "location":"Location 23",
    "active_on_hand_qty":447,
    "active_allocated_qty":4,
    "active_tbf_qty":0,
    "reserve_on_hand_qty":800,
    "reserve_allocated_qty":0,
    "reserve_tbf_qty":0,
    "transitional_qty":0,
    "unallocatable_qty":0,
    "drop_zone_on_hand_qty":0,
    "drop_zone_allocated_qty":0,
    "open_replen_tasks":0,
    "open_putaway_tasks":0,
    "open_asn_qty":0,
    "location_accuracy_score":0.8
  },
  {  
    "facility_id":1,
    "type":"User Short",
    "root_cause":"Invn Accuracy",
    "wave_number":"Wave 4",
    "order_number":"Order 9",
    "order_status":"In Packing",
    "line_status":"Cancelled",
    "sku":"Item 8",
    "sku_description":"Item 8 Description",
    "std_sku_qty":1,
    "ordered_qty":1,
    "allocated_qty":1,
    "packed_qty":0,
    "shorted_qty":1,
    "shorted_by":"User 9",
    "shorted_datetime":"2016-09-20T00:00:20.000Z",
    "location":"Location 24",
    "active_on_hand_qty":0,
    "active_allocated_qty":18,
    "active_tbf_qty":31,
    "reserve_on_hand_qty":339,
    "reserve_allocated_qty":31,
    "reserve_tbf_qty":0,
    "transitional_qty":0,
    "unallocatable_qty":0,
    "drop_zone_on_hand_qty":0,
    "drop_zone_allocated_qty":0,
    "open_replen_tasks":0,
    "open_putaway_tasks":0,
    "open_asn_qty":0,
    "location_accuracy_score":0.67
  },
  {  
    "facility_id":1,
    "type":"User Short",
    "root_cause":"Replenishment",
    "wave_number":"Wave 5",
    "order_number":"Order 10",
    "order_status":"In Packing",
    "line_status":"Cancelled",
    "sku":"Item 9",
    "sku_description":"Item 9 Description",
    "std_sku_qty":1,
    "ordered_qty":1,
    "allocated_qty":1,
    "packed_qty":0,
    "shorted_qty":1,
    "shorted_by":"User 10",
    "shorted_datetime":"2016-09-20T00:00:22.000Z",
    "location":"Location 25",
    "active_on_hand_qty":60,
    "active_allocated_qty":2,
    "active_tbf_qty":60,
    "reserve_on_hand_qty":60,
    "reserve_allocated_qty":60,
    "reserve_tbf_qty":0,
    "transitional_qty":0,
    "unallocatable_qty":0,
    "drop_zone_on_hand_qty":0,
    "drop_zone_allocated_qty":0,
    "open_replen_tasks":0,
    "open_putaway_tasks":1,
    "open_asn_qty":6,
    "location_accuracy_score":0.36
  },
  {  
    "facility_id":1,
    "type":"Allocation Short",
    "root_cause":"Receiving",
    "wave_number":"Wave 2",
    "order_number":"Order 3",
    "order_status":"DC Allocated",
    "line_status":"Cancelled",
    "sku":"Item 13",
    "sku_description":"Item 13 Description",
    "std_sku_qty":1,
    "ordered_qty":1,
    "allocated_qty":0,
    "packed_qty":0,
    "shorted_qty":1,
    "shorted_by":"Wave",
    "shorted_datetime":"2016-09-22T23:51:45.000Z",
    "location":"Location 11",
    "active_on_hand_qty":0,
    "active_allocated_qty":2,
    "active_tbf_qty":0,
    "reserve_on_hand_qty":0,
    "reserve_allocated_qty":0,
    "reserve_tbf_qty":0,
    "transitional_qty":0,
    "unallocatable_qty":0,
    "drop_zone_on_hand_qty":0,
    "drop_zone_allocated_qty":0,
    "open_replen_tasks":1,
    "open_putaway_tasks":1,
    "open_asn_qty":0,
    "location_accuracy_score":0.9
  },
  {  
    "facility_id":1,
    "type":"Allocation Short",
    "root_cause":"Configuration",
    "wave_number":"Wave 2",
    "order_number":"Order 4",
    "order_status":"DC Allocated",
    "line_status":"Cancelled",
    "sku":"Item 2",
    "sku_description":"Item 2 Description",
    "std_sku_qty":1,
    "ordered_qty":6,
    "allocated_qty":0,
    "packed_qty":0,
    "shorted_qty":6,
    "shorted_by":"Wave",
    "shorted_datetime":"2016-09-22T23:53:29.000Z",
    "location":"Location 23",
    "active_on_hand_qty":3,
    "active_allocated_qty":3,
    "active_tbf_qty":0,
    "reserve_on_hand_qty":48,
    "reserve_allocated_qty":48,
    "reserve_tbf_qty":48,
    "transitional_qty":0,
    "unallocatable_qty":0,
    "drop_zone_on_hand_qty":0,
    "drop_zone_allocated_qty":0,
    "open_replen_tasks":0,
    "open_putaway_tasks":0,
    "open_asn_qty":10,
    "location_accuracy_score":0.87
  },
  {  
    "facility_id":1,
    "type":"Allocation Short",
    "root_cause":"Putaway",
    "wave_number":"Wave 2",
    "order_number":"Order 5",
    "order_status":"DC Allocated",
    "line_status":"Cancelled",
    "sku":"Item 9",
    "sku_description":"Item 9 Description",
    "std_sku_qty":1,
    "ordered_qty":1,
    "allocated_qty":0,
    "packed_qty":0,
    "shorted_qty":1,
    "shorted_by":"Wave",
    "shorted_datetime":"2016-09-20T00:00:22.000Z",
    "location":"Location 84",
    "active_on_hand_qty":0,
    "active_allocated_qty":2,
    "active_tbf_qty":0,
    "reserve_on_hand_qty":0,
    "reserve_allocated_qty":0,
    "reserve_tbf_qty":0,
    "transitional_qty":0,
    "unallocatable_qty":0,
    "drop_zone_on_hand_qty":50,
    "drop_zone_allocated_qty":0,
    "open_replen_tasks":0,
    "open_putaway_tasks":0,
    "open_asn_qty":50,
    "location_accuracy_score":0.97
  }
]